aa_bb/__init__.py
aa_bb/admin.py
aa_bb/app_settings.py
aa_bb/apps.py
aa_bb/auth_hooks.py
aa_bb/celery.py
aa_bb/esi_cache.py
aa_bb/esi_client.py
aa_bb/forms.py
aa_bb/models.py
aa_bb/signals.py
aa_bb/tasks.py
aa_bb/tasks_bot.py
aa_bb/tasks_cb.py
aa_bb/tasks_ct.py
aa_bb/tasks_other.py
aa_bb/tasks_tickets.py
aa_bb/tasks_utils.py
aa_bb/urls.py
aa_bb/urls_cb.py
aa_bb/urls_loa.py
aa_bb/urls_paps.py
aa_bb/views.py
aa_bb/views_cb.py
aa_bb/views_faq.py
aa_bb/views_paps.py
aa_bb/checks/__init__.py
aa_bb/checks/add_to_blacklist.py
aa_bb/checks/alliance_blacklist.py
aa_bb/checks/alpha_skills.json
aa_bb/checks/awox.py
aa_bb/checks/clone_state.py
aa_bb/checks/coalition_blacklist.py
aa_bb/checks/corp_changes.py
aa_bb/checks/cyno.py
aa_bb/checks/hostile_assets.py
aa_bb/checks/hostile_clones.py
aa_bb/checks/roles_and_tokens.py
aa_bb/checks/skills.json
aa_bb/checks/skills.py
aa_bb/checks/sus_contacts.py
aa_bb/checks/sus_contracts.py
aa_bb/checks/sus_mails.py
aa_bb/checks/sus_trans.py
aa_bb/checks_cb/__init__.py
aa_bb/checks_cb/hostile_assets.py
aa_bb/checks_cb/sus_contracts.py
aa_bb/checks_cb/sus_trans.py
aa_bb/locale/.gitkeep
aa_bb/management/__init__.py
aa_bb/management/commands/__init__.py
aa_bb/management/commands/bb_purge_entity_cache.py
aa_bb/migrations/0001_initial.py
aa_bb/migrations/0002_bigbrotherconfig_userstatus.py
aa_bb/migrations/0003_alter_bigbrotherconfig_pingroleid.py
aa_bb/migrations/0004_alter_bigbrotherconfig_is_active_and_more.py
aa_bb/migrations/0005_alter_bigbrotherconfig_hostile_alliances.py
aa_bb/migrations/0006_alter_bigbrotherconfig_pingroleid.py
aa_bb/migrations/0007_alter_general_options.py
aa_bb/migrations/0008_alliance_names_corporation_names.py
aa_bb/migrations/0009_userstatus_sus_contacts_userstatus_sus_contracts_and_more.py
aa_bb/migrations/0010_alter_userstatus_awox_kill_links_and_more.py
aa_bb/migrations/0011_character_names.py
aa_bb/migrations/0012_id_types.py
aa_bb/migrations/0013_bigbrotherconfig_mail_keywords.py
aa_bb-3.2.10.dist-info/METADATA
aa_bb-3.2.10.dist-info/WHEEL
aa_bb-3.2.10.dist-info/licenses/LICENSE
aa_bb-3.2.10.dist-info/RECORD
