Metadata-Version: 2.4
Name: aa_bb
Version: 3.2.10
Summary: BigBrother
Project-URL: Changelog, https://github.com/BroodLK/aa_bb/blob/main/CHANGELOG.md
Project-URL: Issue / Bug Reports, https://github.com/BroodLK/aa_bb/issues
Author-email: BioBrute <broodlk@gmail.com>, Andrew Xadi <andrewxadi@gmail.com>
License: Copyright 2025 Andrew Xadi
License-File: LICENSE
Keywords: aa_bb,allianceauth
Classifier: Environment :: Web Environment
Classifier: Framework :: Django
Classifier: Framework :: Django :: 4.2
Classifier: Intended Audience :: Developers
Classifier: License :: OSI Approved :: GNU General Public License v3 (GPLv3)
Classifier: Operating System :: OS Independent
Classifier: Programming Language :: Python
Classifier: Programming Language :: Python :: 3 :: Only
Classifier: Programming Language :: Python :: 3.10
Classifier: Programming Language :: Python :: 3.11
Classifier: Programming Language :: Python :: 3.12
Classifier: Programming Language :: Python :: 3.13
Classifier: Topic :: Internet :: WWW/HTTP
Classifier: Topic :: Internet :: WWW/HTTP :: Dynamic Content
Requires-Python: >=3.10
Requires-Dist: allianceauth-corptools>=2.12.0
Requires-Dist: allianceauth>=4.3.1
Requires-Dist: django-esi>=8.2.0
Requires-Dist: matplotlib>=3.7.2
